pyborg/__init__.py
pyborg/commands.py
pyborg/mod/__init__.py
pyborg/mod/mod_discord.py
pyborg/mod/mod_filein.py
pyborg/mod/mod_http.py
pyborg/mod/mod_irc.py
pyborg/mod/mod_linein.py
pyborg/mod/mod_mastodon.py
pyborg/mod/mod_reddit.py
pyborg/mod/mod_subtitle.py
pyborg/mod/mod_tumblr.py
pyborg/mod/mod_twitter.py
pyborg/pyborg.py
pyborg/util/__init__.py
pyborg/util/awoo.py
pyborg/util/bottle_plugin.py
pyborg/util/censored_defaults.py
pyborg/util/commands.py
pyborg/util/config_defaults.py
pyborg/util/elenco_cognomi.txt
pyborg/util/elenco_nomi.txt
pyborg/util/graphing.py
pyborg/util/hate_filter.py
pyborg/util/keybase_chat.py
pyborg/util/stats.py
pyborg/util/util_cli.py
pyborg/util/utils_testing.py
pyborg_entrypoint.py
pyborg-2.0.0.dist-info/entry_points.txt
pyborg-2.0.0.dist-info/LICENSE
pyborg-2.0.0.dist-info/WHEEL
pyborg-2.0.0.dist-info/METADATA
pyborg-2.0.0.dist-info/RECORD
